Minting/__init__.py
Minting/client.py
minting-2.2.2.dist-info/METADATA
minting-2.2.2.dist-info/WHEEL
minting-2.2.2.dist-info/top_level.txt
minting-2.2.2.dist-info/RECORD
