Metadata-Version: 2.4
Name: minting
Version: 2.2.2
Summary: Mintzy SDK for stock price prediction
Author: Om Kulthe
Author-email: mintzy01.ai@gmail.com
Classifier: Programming Language :: Python :: 3
Classifier: License :: OSI Approved :: MIT License
Requires-Python: >=3.7
Requires-Dist: requests>=2.25.0
Requires-Dist: pymongo>=4.0.0
Requires-Dist: pandas>=1.3.0
Requires-Dist: flask>=2.0.0
Dynamic: author
Dynamic: author-email
Dynamic: classifier
Dynamic: requires-dist
Dynamic: requires-python
Dynamic: summary
